regex_recipes/__init__.py
regex_recipes/builder.py
regex_recipes/components.py
regex_recipes/example.py
regex_recipes-0.1.0.dist-info/licenses/LICENCE
regex_recipes-0.1.0.dist-info/METADATA
regex_recipes-0.1.0.dist-info/WHEEL
regex_recipes-0.1.0.dist-info/top_level.txt
regex_recipes-0.1.0.dist-info/RECORD
