Metadata-Version: 2.4
Name: regex-recipes
Version: 0.1.0
Summary: A fluent, composable API for building regular expressions
Author: Aditya Kulkarni
Maintainer: Aditya Kulkarni
License: MIT
Project-URL: Homepage, https://github.com/adityavkulkarni/regex-recipes
Project-URL: Documentation, https://github.com/adityavkulkarni/regex-recipes#readme
Project-URL: Repository, https://github.com/adityavkulkarni/regex-recipes
Project-URL: Issues, https://github.com/adityavkulkarni/regex-recipes/issues
Keywords: regex,regular-expressions,pattern-matching,fluent-api,builder
Classifier: Development Status :: 3 - Alpha
Classifier: Intended Audience :: Developers
Classifier: License :: OSI Approved :: MIT License
Classifier: Operating System :: OS Independent
Classifier: Programming Language :: Python :: 3
Classifier: Programming Language :: Python :: 3.8
Classifier: Programming Language :: Python :: 3.9
Classifier: Programming Language :: Python :: 3.10
Classifier: Programming Language :: Python :: 3.11
Classifier: Programming Language :: Python :: 3.12
Classifier: Topic :: Software Development :: Libraries :: Python Modules
Classifier: Topic :: Text Processing
Classifier: Typing :: Typed
Requires-Python: >=3.8
License-File: LICENCE
Provides-Extra: dev
Requires-Dist: pytest>=7.0.0; extra == "dev"
Requires-Dist: pytest-cov>=4.0.0; extra == "dev"
Requires-Dist: black>=23.0.0; extra == "dev"
Requires-Dist: mypy>=1.0.0; extra == "dev"
Requires-Dist: ruff>=0.1.0; extra == "dev"
Dynamic: license-file
